pyliverlesionseg/__init__.py
pyliverlesionseg/cnn_liver_lesion_seg_CT_MR_functions.py
pyliverlesionseg/dcm_server_liver_lesion_seg.py
pyliverlesionseg/dcm_server_liver_seg.py
pyliverlesionseg/general.py
pyliverlesionseg/predict_liver_lesion_seg.py
pyliverlesionseg/train_liver_lesion_seg.py
pyliverlesionseg/architectures/__init__.py
pyliverlesionseg/architectures/unet_generalized.py
pyliverlesionseg/components/__init__.py
pyliverlesionseg/components/callbacks.py
pyliverlesionseg/components/layer_resolution.py
pyliverlesionseg/components/loss.py
pyliverlesionseg/components/metrics.py
pyliverlesionseg/sampling/__init__.py
pyliverlesionseg/sampling/affinedeformation.py
pyliverlesionseg/sampling/generator.py
pyliverlesionseg/sampling/imageloader.py
pyliverlesionseg/sampling/imagetransformer.py
pyliverlesionseg/sampling/randomdeformation.py
pyliverlesionseg/sampling/randomness.py
pyliverlesionseg/sampling/samplecreator.py
pyliverlesionseg/sampling/sampler.py
pyliverlesionseg/sampling/sampletransformer.py
pyliverlesionseg/trained_models/model_unet_ct_mr_lesion_seg_resize_1mm_1mm_3mm_20220207_dice_loss_val_binary_dice_mean.hdf5
pyliverlesionseg/trained_models/model_unet_ct_mr_liv_seg_resize_1.5mm_med_3_resize_3mm_20201011_dice_loss_val_binary_dice_mean.hdf5
pyliverlesionseg-0.3.dist-info/LICENSE
pyliverlesionseg-0.3.dist-info/METADATA
pyliverlesionseg-0.3.dist-info/WHEEL
pyliverlesionseg-0.3.dist-info/entry_points.txt
pyliverlesionseg-0.3.dist-info/top_level.txt
pyliverlesionseg-0.3.dist-info/RECORD
