Metadata-Version: 2.1
Name: pyliverlesionseg
Version: 0.3
Summary: CNN-based whole liver and liver lesion segmentation in CT and MR
Home-page: https://github.com/KUL-recon-lab/pyliverlesionseg
Author: Xikai Tang and Georg Schramm
Author-email: xikai.tang@kuleuven.be, georg.schramm@kuleuven.be
License: Apache License 2.0
Platform: UNKNOWN
Classifier: Programming Language :: Python :: 3
Classifier: License :: OSI Approved :: Apache Software License
Classifier: Operating System :: OS Independent
Requires-Python: >=3.6, <3.7
License-File: LICENSE
Requires-Dist: h5py (==2.10)
Requires-Dist: tensorflow (==1.12.0)
Requires-Dist: keras (==2.2.4)
Requires-Dist: pymirc (>=0.27)
Requires-Dist: pynetdicom (>=1.5)
